Workbook

Sheet 投资汇总表
A1: 光储充电站投资预算汇总表
A2: 单位：元
A3: 序号 | B3: 分项 | C3: 合价
A4: 1 | B4: 光伏发电部分 | C4: =投资汇总表!I20 -> 149910
A5: 2 | B5: 储能部分 | C5: =投资汇总表!I28 -> 150737
A6: 3 | B6: 充电桩部分 | C6: =投资汇总表!I34 -> 4131.2
A7: 4 | B7: 钢构及接地部分 | C7: =投资汇总表!I39 -> 270160
A8: 合计： | C8: =SUM(C4:C7) -> 574938.2
A10: 主要设备投资预算表
A11: 设备名称 | B11: 规格、型号 | C11: 单位 | D11: 数量 | E11: 材料单价 | F11: 材料合价 | G11: 安装单价 | H11: 安装合价 | I11: 单项合价 | J11: 备注
A12: 一、光伏发电部分
A13: 单晶光伏组件 | B13: 350W，多主栅PERC半片组件，1689*996*35,6*20，20.8% | C13: 块 | D13: 126 | E13: =2*350 -> 700 | F13: =D13*E13 -> 88200 | G13: 60 | H13: =D13*G13 -> 7560 | I13: =F13+H13 -> 95760
A14: 光伏支架 | B14: 铝合金，含导轨、夹具、压块 | C14: 套 | D14: 1 | E14: =0.4*44100 -> 17640 | F14: =D14*E14 -> 17640 | G14: 6200 | H14: =D14*G14 -> 6200 | I14: =F14+H14 -> 23840
A15: 逆变器 | B15: EA25KTSI,组串式逆变器 | C15: 台 | D15: 2 | E15: 8300 | F15: =D15*E15 -> 16600 | G15: 200 | H15: =D15*G15 -> 400 | I15: =F15+H15 -> 17000
A16: 光伏电缆 | B16: PF-1*4mm | C16: 米 | D16: 800 | E16: 3 | F16: =D16*E16 -> 2400 | G16: 1.5 | H16: =D16*G16 -> 1200 | I16: =F16+H16 -> 3600
A17: 电力电缆 | B17: ZR-YJV-0.6/1KV-4*25+1*16mm | C17: 米 | D17: 100 | E17: 46 | F17: =D17*E17 -> 4600 | G17: 4 | H17: =D17*G17 -> 400 | I17: =F17+H17 -> 5000
A18: 组串引出线接插件 | B18: MC4 | C18: 套 | D18: 40 | E18: 5 | F18: =D18*E18 -> 200 | G18: 4 | H18: =D18*G18 -> 160 | I18: =F18+H18 -> 360
A19: 并网柜 | B19: 50KW，详见图纸 | C19: 台 | D19: 1 | E19: 3850 | F19: =D19*E19 -> 3850 | G19: 500 | H19: =D19*G19 -> 500 | I19: =F19+H19 -> 4350
A20: 小计 | I20: =SUM(I13:I19) -> 149910
A21: 二、储能部分
A22: 储能变流器 | B22: EAPCS 50K | C22: 台 | D22: 1 | E22: 16525 | F22: =D22*E22 -> 16525 | G22: 260 | H22: =D22*G22 -> 260 | I22: =F22+H22 -> 16785
A23: 磷酸铁锂电池 | B23: 3.2V/50Ah | C23: KWH | D23: 76.8 | E23: 1380 | F23: =D23*E23 -> 105984 | G23: 10 | H23: =D23*G23 -> 768 | I23: =F23+H23 -> 106752
A24: 电池柜 | B24: 535*670*2200，带直流开关 | C24: 台 | D24: 1 | E24: 2800 | F24: =D24*E24 -> 2800 | G24: 100 | H24: =D24*G24 -> 100 | I24: =F24+H24 -> 2900
A25: 电池连接线 | C25: 套 | D25: 1 | E25: 1600 | F25: =D25*E25 -> 1600 | G25: 300 | H25: =D25*G25 -> 300 | I25: =F25+H25 -> 1900
A26: EMS能量管理系统 | B26: 定制 | C26: 套 | D26: 1 | E26: 20000 | F26: =D26*E26 -> 20000 | H26: =D26*G26 -> 0 | I26: =F26+H26 -> 20000
A27: 储能交流电缆 | B27: ZR-YJV-0.6/1KV-4*25+1*16m | C27: 米 | D27: 30 | E27: 75 | F27: =D27*E27 -> 2250 | G27: 5 | H27: =D27*G27 -> 150 | I27: =F27+H27 -> 2400
A28: 小计 | I28: =SUM(I22:I27) -> 150737
A29: 三、充电桩部分
A30: 充电桩 | B30: 7KVA，单枪，立式充电桩 | C30: 台 | D30: 1 | E30: 3126.2 | F30: =D30*E30 -> 3126.2 | G30: 180 | H30: =D30*G30 -> 180 | I30: =F30+H30 -> 3306.2
A31: 发卡机 | C31: 台 | D31: 1 | E31: 300 | F31: =D31*E31 -> 300 | G31: 55 | H31: =D31*G31 -> 55 | I31: =F31+H31 -> 355
A32: 充电卡 | C32: 张 | D32: 5 | E32: 10 | F32: =D32*E32 -> 50 | G32: 0 | H32: =D32*G32 -> 0 | I32: =F32+H32 -> 50
A33: 电力电缆 | B33: 1*10 | C33: 米 | D33: 60 | E33: 5 | F33: =D33*E33 -> 300 | G33: 2 | H33: =D33*G33 -> 120 | I33: =F33+H33 -> 420
A34: 小计 | I34: =SUM(I30:I33) -> 4131.2
A35: 四、钢构及接地部分
A36: 钢结构 | B36: 预估价，含梁、柱、屋面等材料 | C36: 平方米 | D36: =15*16 -> 240 | E36: 700 | F36: =D36*E36 -> 168000 | G36: 400 | H36: =D36*G36 -> 96000 | I36: =F36+H36 -> 264000
A37: 接地扁钢 | B37: 40*4 Q235B | C37: 米 | D37: 320 | E37: 12 | F37: =D37*E37 -> 3840 | G37: 5 | H37: =D37*G37 -> 1600 | I37: =F37+H37 -> 5440
A38: 接地线 | B38: φ16圆钢 L=1.5M | C38: 米 | D38: 60 | E38: 8 | F38: =D38*E38 -> 480 | G38: 4 | H38: =D38*G38 -> 240 | I38: =F38+H38 -> 720
A39: 小计 | I39: =SUM(I36:I38) -> 270160
A43: 年均发电量测算表
A44: 项目名称 | B44: 年平均 | C44: 合计 | D44: 第1年 | E44: 第2年 | F44: 第3年 | G44: 第4年 | H44: 第5年 | I44: 第6年 | J44: 第7年 | K44: 第8年 | L44: 第9年 | M44: 第10年 | N44: 第11年 | O44: 第12年 | P44: 第13年
A45: 组件衰减后组件功率比率 | B45: =AVERAGE(D45:P45,D52:O52) -> 0.882 | D45: =100%-2% -> 0.98 | E45: =D45-2% -> 0.96 | F45: =E45-6%/8 -> 0.9525 | G45: =F45-6%/8 -> 0.945 | H45: =G45-6%/8 -> 0.9375 | I45: =H45-6%/8 -> 0.93 | J45: =I45-6%/8 -> 0.9225 | K45: =J45-6%/8 -> 0.915 | L45: =K45-6%/8 -> 0.9075 | M45: =L45-6%/8 -> 0.9 | N45: =M45-10%/15 -> 0.89333333 | O45: =N45-10%/15 -> 0.88666667 | P45: =O45-10%/15 -> 0.88
A46: 实际发电电量（万kwh） | B46: =AVERAGE(D46:P46,D53:O53) -> 3.4920476 | C46: =SUM(D46:P46,D53:O53) -> 87.30119 | D46: =B73*D45 -> 3.8800529 | E46: =B73*E45 -> 3.8008681 | F46: =B73*F45 -> 3.7711738 | G46: =B73*G45 -> 3.7414796 | H46: =B73*H45 -> 3.7117853 | I46: =B73*I45 -> 3.682091 | J46: =B73*J45 -> 3.6523967 | K46: =B73*K45 -> 3.6227024 | L46: =B73*L45 -> 3.5930081 | M46: =B73*M45 -> 3.5633139 | N46: =B73*N45 -> 3.5369189 | O46: =B73*O45 -> 3.510524 | P46: =B73*P45 -> 3.4841291
A47: 自发自用电量（万kwh） | B47: =AVERAGE(D47:P47,D54:O54) -> 2.7936381 | C47: =SUM(D47:P47,D54:O54) -> 69.840952 | D47: =D46*B74 -> 3.1040423 | E47: =E46*B74 -> 3.0406945 | F47: =F46*B74 -> 3.0169391 | G47: =G46*B74 -> 2.9931836 | H47: =H46*B74 -> 2.9694282 | I47: =I46*B74 -> 2.9456728 | J47: =J46*B74 -> 2.9219174 | K47: =K46*B74 -> 2.8981619 | L47: =L46*B74 -> 2.8744065 | M47: =M46*B74 -> 2.8506511 | N47: =N46*B74 -> 2.8295352 | O47: =O46*B74 -> 2.8084192 | P47: =P46*B74 -> 2.7873033
A48: 剩余上网电量（万kwh） | B48: =AVERAGE(D48:P48,D55:O55) -> 0.69840952 | C48: =SUM(D48:P48,D55:O55) -> 17.460238 | D48: =D46*(1-B74) -> 0.77601057 | E48: =E46*(1-B74) -> 0.76017362 | F48: =F46*(1-B74) -> 0.75423477 | G48: =G46*(1-B74) -> 0.74829591 | H48: =H46*(1-B74) -> 0.74235705 | I48: =I46*(1-B74) -> 0.7364182 | J48: =J46*(1-B74) -> 0.73047934 | K48: =K46*(1-B74) -> 0.72454048 | L48: =L46*(1-B74) -> 0.71860163 | M48: =M46*(1-B74) -> 0.71266277 | N48: =N46*(1-B74) -> 0.70738379 | O48: =O46*(1-B74) -> 0.7021048 | P48: =P46*(1-B74) -> 0.69682582
A49: 发电收益（万元） | B49: =AVERAGE(D49:P49,D56:O56) -> 2.7622096 | C49: =SUM(D49:P49,D56:O56) -> 69.055241 | D49: =D47*B75+B76*D48 -> 3.0691218 | E49: =E47*B75+B76*E48 -> 3.0064867 | F49: =F47*B75+B76*F48 -> 2.9829985 | G49: =G47*B75+B76*G48 -> 2.9595103 | H49: =H47*B75+B76*H48 -> 2.9360221 | I49: =I47*B75+B76*I48 -> 2.912534 | J49: =J47*B75+B76*J48 -> 2.8890458 | K49: =K47*B75+B76*K48 -> 2.8655576 | L49: =L47*B75+B76*L48 -> 2.8420694 | M49: =M47*B75+B76*M48 -> 2.8185813 | N49: =N47*B75+B76*N48 -> 2.7977029 | O49: =O47*B75+B76*O48 -> 2.7768245 | P49: =P47*B75+B76*P48 -> 2.7559461
A51: 项目名称 | B51: 年平均 | C51: 合计 | D51: 第14年 | E51: 第15年 | F51: 第16年 | G51: 第17年 | H51: 第18年 | I51: 第19年 | J51: 第20年 | K51: 第21年 | L51: 第22年 | M51: 第23年 | N51: 第24年 | O51: 第25年
A52: 组件衰减后组件功率比率 | B52: =B45 -> 0.882 | D52: =P45-10%/15 -> 0.87333333 | E52: =D52-10%/15 -> 0.86666667 | F52: =E52-10%/15 -> 0.86 | G52: =F52-10%/15 -> 0.85333333 | H52: =G52-10%/15 -> 0.84666667 | I52: =H52-10%/15 -> 0.84 | J52: =I52-10%/15 -> 0.83333333 | K52: =J52-10%/15 -> 0.82666667 | L52: =K52-10%/15 -> 0.82 | ... O52: =N52-10%/15 -> 0.8
A53: 实际发电电量（万kwh） | B53: =B46 -> 3.4920476 | C53: =C46 -> 87.30119 | D53: =B73*D52 -> 3.4577342 | E53: =B73*E52 -> 3.4313393 | F53: =B73*F52 -> 3.4049444 | G53: =B73*G52 -> 3.3785494 | H53: =B73*H52 -> 3.3521545 | I53: =B73*I52 -> 3.3257596 | J53: =B73*J52 -> 3.2993647 | K53: =B73*K52 -> 3.2729698 | L53: =B73*L52 -> 3.2465748 | M53: =B73*M52 -> 3.2201799 | N53: =B73*N52 -> 3.193785 | O53: =B73*O52 -> 3.1673901
A54: 自发自用电量（万kwh） | B54: =B47 -> 2.7936381 | C54: =C47 -> 69.840952 | D54: =D53*B74 -> 2.7661874 | E54: =E53*B74 -> 2.7450714 | F54: =F53*B74 -> 2.7239555 | G54: =G53*B74 -> 2.7028395 | H54: =H53*B74 -> 2.6817236 | I54: =I53*B74 -> 2.6606077 | J54: =J53*B74 -> 2.6394917 | K54: =K53*B74 -> 2.6183758 | L54: =L53*B74 -> 2.5972599 | M54: =M53*B74 -> 2.5761439 | N54: =N53*B74 -> 2.555028 | O54: =O53*B74 -> 2.5339121
A55: 剩余上网电量（万kwh） | B55: =B48 -> 0.69840952 | C55: =C48 -> 17.460238 | D55: =D53*(1-B74) -> 0.69154684 | E55: =E53*(1-B74) -> 0.68626785 | F55: =F53*(1-B74) -> 0.68098887 | G55: =G53*(1-B74) -> 0.67570989 | H55: =H53*(1-B74) -> 0.6704309 | I55: =I53*(1-B74) -> 0.66515192 | J55: =J53*(1-B74) -> 0.65987294 | K55: =K53*(1-B74) -> 0.65459395 | L55: =L53*(1-B74) -> 0.64931497 | M55: =M53*(1-B74) -> 0.64403599 | N55: =N53*(1-B74) -> 0.638757 | O55: =O53*(1-B74) -> 0.63347802
A56: 发电收益（万元） | B56: =B49 -> 2.7622096 | C56: =C49 -> 69.055241 | D56: =D54*B75+B76*D55 -> 2.7350677 | E56: =E54*B75+B76*E55 -> 2.7141894 | F56: =F54*B75+B76*F55 -> 2.693311 | G56: =G54*B75+B76*G55 -> 2.6724326 | H56: =H54*B75+B76*H55 -> 2.6515542 | I56: =I54*B75+B76*I55 -> 2.6306758 | J56: =J54*B75+B76*J55 -> 2.6097975 | K56: =K54*B75+B76*K55 -> 2.5889191 | L56: =L54*B75+B76*L55 -> 2.5680407 | M56: =M54*B75+B76*M55 -> 2.5471623 | N56: =N54*B75+B76*N55 -> 2.5262839 | O56: =O54*B75+B76*O55 -> 2.5054056
A58: 光伏发电站测算表
A59: 电站总功率 | B59: 44100 | C59: W
A60: 电池板面积： | B60: 1.65 | C60: m2
A61: 每片瓦数 | B61: 350 | C61: W
A62: 每组片数 | B62: 21 | C62: 片
A63: 每组瓦数 | B63: =B62*B61 -> 7350 | C63: W
A64: 共有组数 | B64: =B59/B63 -> 6 | C64: 组
A65: 电池板数量： | B65: =B59/B61 -> 126 | C65: 个
A66: 电池板数量： | B66: =B65 -> 126 | C66: 个
A67: 单位面积年辐射 | B67: 1368.1 | C67: kWh/m2
A68: 单位面积年辐射量 | B68: =B67*3.6 -> 4925.16 | C68: MJ/m2
A69: 电池板总面积 | B69: =B60*B66 -> 207.9 | C69: m2
A70: 年电池板辐射量： | B70: =B67*B69 -> 284427.99 | C70: kWh
A71: 转换率： | B71: =IF(B61=60,7.6%,17.4%) -> 0.174
A72: 组件效率 | B72: 0.8
A73: 首年发电量不考虑衰减 | B73: =B70*B72*B71/10000 -> 3.9592376 | C73: 万kwh
A74: 自用电比例 | B74: 0.8
A75: 自用电电价 | B75: 0.9 | C75: 元/KWH
A76: 上网电价 | B76: 0.355 | C76: 元/KWH
A80: 光伏收益模型-成本项
A81: 序号 | B81: 分项 | C81: 说明 | D81: 数值 | E81: 单位
A82: 1 | B82: 光伏电站综合单价 | C82: 仅计算光伏部分 | D82: =D84/D83 -> 3.3993197 | E82: 元/瓦
A83: 2 | B83: 装机容量 | D83: 44100 | E83: 瓦
A84: 3 | B84: 总投资 | D84: =投资汇总表!I20 -> 149910 | E84: 元
A85: 4 | B85: 光伏电站年均发电量 | D85: =投资汇总表!B46*10000 -> 34920.476 | E85: 度
A86: 5 | B86: 年设备维护费 | C86: 总投资*3% | D86: =D84*3% -> 4497.3 | E86: 元
A87: 6 | B87: 年折旧费 | C87: 折旧年限25年 | D87: =D84*(1-5%)/25 -> 5696.58 | E87: 元
A88: 7 | B88: 年各类费用合计 | D88: =D86+D87 -> 10193.88 | E88: 元
A92: 资金内部收益率
A93: 项目总投资 | B93: =-投资汇总表!D84 -> -149910 | C93: IRR
A94: 第一年净收益 | B94: =#REF!+投资汇总表!D49*10000-投资汇总表!D86 -> #REF! | C94: =IRR(B93:B94) -> #VALUE!
A95: 第二年净收益 | B95: =#REF!+投资汇总表!E49*10000-投资汇总表!D86 -> #REF! | C95: =IRR(B93:B95) -> #VALUE!
A96: 第三年净收益 | B96: =#REF!+投资汇总表!F49*10000-投资汇总表!D86 -> #REF! | C96: =IRR(B93:B96) -> #VALUE!
A97: 第四年净收益 | B97: =#REF!+投资汇总表!G49*10000-投资汇总表!D86 -> #REF! | C97: =IRR(B93:B97) -> #VALUE!
A98: 第五年净收益 | B98: =#REF!+投资汇总表!H49*10000-投资汇总表!D86 -> #REF! | C98: =IRR(B93:B98) -> #VALUE!
A99: 第六年净收益 | B99: =#REF!+投资汇总表!I49*10000-投资汇总表!D86 -> #REF! | C99: =IRR(B93:B99) -> #VALUE!
A100: 第七年净收益 | B100: =#REF!+投资汇总表!J49*10000-投资汇总表!D86 -> #REF! | C100: =IRR(B93:B100) -> #VALUE!
A101: 第八年净收益 | B101: =#REF!+投资汇总表!K49*10000-投资汇总表!D86 -> #REF! | C101: =IRR(B93:B101) -> #VALUE!
A102: 第九年净收益 | B102: =#REF!+投资汇总表!L49*10000-投资汇总表!D86 -> #REF! | C102: =IRR(B93:B102) -> #VALUE!
A103: 第十年净收益 | B103: =#REF!+投资汇总表!M49*10000-投资汇总表!D86 -> #REF! | C103: =IRR(B93:B103) -> #VALUE!
A104: 第十一年净收益 | B104: =#REF!+投资汇总表!N49*10000-投资汇总表!D86 -> #REF! | C104: =IRR(B93:B104) -> #VALUE!
A105: 第十二年净收益 | B105: =#REF!+投资汇总表!O49*10000-投资汇总表!D86 -> #REF! | C105: =IRR(B93:B105) -> #VALUE!
A106: 第十三年净收益 | B106: =#REF!+投资汇总表!P49*10000-投资汇总表!D86 -> #REF! | C106: =IRR(B93:B106) -> #VALUE!
A107: 第十四年净收益 | B107: =#REF!+投资汇总表!D56*10000-投资汇总表!D86 -> #REF! | C107: =IRR(B93:B107) -> #VALUE!
A108: 第十五年净收益 | B108: =#REF!+投资汇总表!E56*10000-投资汇总表!D86 -> #REF! | C108: =IRR(B93:B108) -> #VALUE!
A109: 第十六年净收益 | B109: =#REF!+投资汇总表!F56*10000-投资汇总表!D86 -> #REF! | C109: =IRR(B93:B109) -> #VALUE!
A110: 第十七年净收益 | B110: =#REF!+投资汇总表!G56*10000-投资汇总表!D86 -> #REF! | C110: =IRR(B93:B110) -> #VALUE!
A111: 第十八年净收益 | B111: =#REF!+投资汇总表!H56*10000-投资汇总表!D86 -> #REF! | C111: =IRR(B93:B111) -> #VALUE!
A112: 第十九年净收益 | B112: =#REF!+投资汇总表!I56*10000-投资汇总表!D86 -> #REF! | C112: =IRR(B93:B112) -> #VALUE!
...
